faisslite/Faiss.py
faisslite/__init__.py
faisslite/document.py
faisslite/encode.py
faisslite-0.0.4.dist-info/METADATA
faisslite-0.0.4.dist-info/WHEEL
faisslite-0.0.4.dist-info/top_level.txt
faisslite-0.0.4.dist-info/RECORD
