Metadata-Version: 2.1
Name: faisslite
Version: 0.0.4
Summary: 创建/查询Faiss向量数据库
Home-page: https://pypi.org/user/May.xiaoya.zhang/
Author: may.xiaoya.zhang
Author-email: may.xiaoya.zhang@gmail.com
